anyblok_pyramid/__init__.py
anyblok_pyramid/adapter.py
anyblok_pyramid/anyblok.py
anyblok_pyramid/common.py
anyblok_pyramid/config.py
anyblok_pyramid/conftest.py
anyblok_pyramid/gunicorn.py
anyblok_pyramid/pyramid_config.py
anyblok_pyramid/release.py
anyblok_pyramid/scripts.py
anyblok_pyramid/security.py
anyblok_pyramid/testing.py
anyblok_pyramid/wsgi.py
anyblok_pyramid/bloks/__init__.py
anyblok_pyramid/bloks/auth/__init__.py
anyblok_pyramid/bloks/auth/exceptions.py
anyblok_pyramid/bloks/auth/role.py
anyblok_pyramid/bloks/auth/user.py
anyblok_pyramid/bloks/auth/views.py
anyblok_pyramid/bloks/auth/tests/__init__.py
anyblok_pyramid/bloks/auth/tests/conftest.py
anyblok_pyramid/bloks/auth/tests/test_user.py
anyblok_pyramid/bloks/authorization/__init__.py
anyblok_pyramid/bloks/authorization/authorization.py
anyblok_pyramid/bloks/authorization/exceptions.py
anyblok_pyramid/bloks/authorization/query.py
anyblok_pyramid/bloks/authorization/user.py
anyblok_pyramid/bloks/authorization/tests/__init__.py
anyblok_pyramid/bloks/authorization/tests/conftest.py
anyblok_pyramid/bloks/authorization/tests/test_authorization.py
anyblok_pyramid/bloks/authorization/tests/test_check_acl.py
anyblok_pyramid/bloks/authorization/tests/test_get_acl.py
anyblok_pyramid/bloks/authorization/tests/test_query.py
anyblok_pyramid/bloks/authorization/tests/test_validation.py
anyblok_pyramid/bloks/password/__init__.py
anyblok_pyramid/bloks/password/user.py
anyblok_pyramid/bloks/password/tests/__init__.py
anyblok_pyramid/bloks/password/tests/conftest.py
anyblok_pyramid/bloks/password/tests/test_credential.py
anyblok_pyramid/bloks/pyramid/__init__.py
anyblok_pyramid/bloks/pyramid/model.py
anyblok_pyramid/bloks/pyramid/oidc.py
anyblok_pyramid/bloks/pyramid/pyramid.py
anyblok_pyramid/bloks/pyramid/restrict.py
anyblok_pyramid/bloks/user_identity/__init__.py
anyblok_pyramid/bloks/user_identity/user.py
anyblok_pyramid/bloks/user_identity/tests/__init__.py
anyblok_pyramid/bloks/user_identity/tests/conftest.py
anyblok_pyramid-1.2.2.dist-info/LICENSE
anyblok_pyramid-1.2.2.dist-info/METADATA
anyblok_pyramid-1.2.2.dist-info/WHEEL
anyblok_pyramid-1.2.2.dist-info/entry_points.txt
anyblok_pyramid-1.2.2.dist-info/top_level.txt
anyblok_pyramid-1.2.2.dist-info/RECORD
