Metadata-Version: 2.1
Name: anyblok-pyramid
Version: 1.2.2
Summary: Web Server Pyramid for AnyBlok
Home-page: http://docs.anyblok-pyramid.anyblok.org/1.2.2
Author: Jean-Sébastien Suzanne
Author-email: jssuzanne@anybox.fr
License: MPL2
Platform: UNKNOWN
Classifier: Development Status :: 5 - Production/Stable
Classifier: Intended Audience :: Developers
Classifier: Programming Language :: Python :: 3.6
Classifier: Programming Language :: Python :: 3.7
Classifier: Programming Language :: Python :: 3.8
Classifier: Programming Language :: Python :: 3.9
Classifier: Topic :: Software Development :: Libraries :: Python Modules
Classifier: Framework :: Pyramid
Classifier: Topic :: Internet :: WWW/HTTP
Classifier: Topic :: Internet :: WWW/HTTP :: HTTP Servers
Classifier: Topic :: Internet :: WWW/HTTP :: WSGI :: Server
Classifier: License :: OSI Approved :: Mozilla Public License 2.0 (MPL 2.0)
Requires-Dist: anyblok (>=1.1.0)
Requires-Dist: hupper
Requires-Dist: passlib
Requires-Dist: pyramid (<2.0.0)
Requires-Dist: pyramid-tm
Requires-Dist: zope.sqlalchemy
Provides-Extra: oidc
Requires-Dist: oic ; extra == 'oidc'
